{"name":"xd","littleEndian":true,"symbols":{"error":{"parameters":["str"],"result":"str","nonBlocking":false},"calender":{"parameters":["str"],"result":"str","nonBlocking":false},"dialog_box_html":{"parameters":["str","str"],"result":"void","nonBlocking":false},"warning":{"parameters":["str"],"result":"str","nonBlocking":false},"information":{"parameters":["str"],"result":"str","nonBlocking":false},"write_to_clipboard":{"parameters":["str"],"result":"void","nonBlocking":false},"screenshot":{"parameters":["i32","i32","u32"],"result":"str","nonBlocking":true},"read_clipboard":{"parameters":[],"result":"str","nonBlocking":false},"progress":{"parameters":[],"result":"str","nonBlocking":false},"question":{"parameters":["str"],"result":"str","nonBlocking":false},"screenshot_sync":{"parameters":["i32","i32","u32"],"result":"str","nonBlocking":false},"xd":{"parameters":[],"result":"void","nonBlocking":false}},"typeDefs":{"Content":{},"WebViewAttrs":{"incognito":"bool","transparent":"bool","back_forward_navigation_gestures":"bool","clipboard":"bool","initialization_script":"Vec","autoplay":"bool","accept_first_mouse":"bool","devtools":"bool","visible":"bool","user_agent":"String","zoom_hotkeys_enabled":"bool"},"WindowAttrs":{"title":"String","always_on_bottom":"bool","max_inner_size":"Size","closable":"bool","decorations":"bool","inner_size":"Size","preferred_theme":"Theme","content_protection":"bool","transparent":"bool","visible_on_all_workspaces":"bool","maximizable":"bool","resizable":"bool","focused":"bool","minimizable":"bool","visible":"bool","maximized":"bool","min_inner_size":"Size","window_icon":"String","always_on_top":"bool"},"Theme":{},"Size":{"width":"u16","height":"u16"}},"tsTypes":{"Theme":"export type Theme =   \"Light\"  |\n  \"Dark\";","Size":"export type Size = {\n    height: number;\n  width: number;\n};","WebViewAttrs":"export type WebViewAttrs = {\n    user_agent: string;\n  visible: boolean;\n  transparent: boolean;\n  zoom_hotkeys_enabled: boolean;\n  initialization_script: Array<string>;\n  clipboard: boolean;\n  devtools: boolean;\n  accept_first_mouse: boolean;\n  back_forward_navigation_gestures: boolean;\n  incognito: boolean;\n  autoplay: boolean;\n};","WindowAttrs":"export type WindowAttrs = {\n    inner_size: Size;\n  min_inner_size: Size;\n  max_inner_size: Size;\n  resizable: boolean;\n  minimizable: boolean;\n  maximizable: boolean;\n  closable: boolean;\n  title: string;\n  maximized: boolean;\n  visible: boolean;\n  transparent: boolean;\n  decorations: boolean;\n  always_on_top: boolean;\n  always_on_bottom: boolean;\n  window_icon: string;\n  preferred_theme: Theme;\n  focused: boolean;\n  content_protection: boolean;\n  visible_on_all_workspaces: boolean;\n};","Content":"export type Content =  { Html: {\n   html: string;\n} }  |\n { Url: {\n   url: string;\n} };"}}